LICENSE
MANIFEST.in
README.md
requirements.txt
setup.py
src/scKTLD/__init__.py
src/scKTLD/call_display.py
src/scKTLD/cpDector.py
src/scKTLD/metrics_similarity.py
src/scKTLD/nodeEmb.py
src/scKTLD/preprocess.py
src/scKTLD.egg-info/PKG-INFO
src/scKTLD.egg-info/SOURCES.txt
src/scKTLD.egg-info/dependency_links.txt
src/scKTLD.egg-info/requires.txt
src/scKTLD.egg-info/top_level.txt
src/scKTLD/cpd_utils/__init__.py
src/scKTLD/cpd_utils/base.py
src/scKTLD/cpd_utils/costkernel.py
src/scKTLD/cpd_utils/exceptions.py
src/scKTLD/cpd_utils/factory.py
src/scKTLD/cpd_utils/kernelcpd.py
src/scKTLD/cpd_utils/_detection/__init__.py
src/scKTLD/cpd_utils/_detection/ekcpd.c
src/scKTLD/cpd_utils/_detection/ekcpd.pxd
src/scKTLD/cpd_utils/_detection/ekcpd.pyx
src/scKTLD/cpd_utils/_detection/ekcpd_computation.c
src/scKTLD/cpd_utils/_detection/ekcpd_computation.h
src/scKTLD/cpd_utils/_detection/ekcpd_pelt_computation.c
src/scKTLD/cpd_utils/_detection/ekcpd_pelt_computation.h
src/scKTLD/cpd_utils/_detection/kernels.c
src/scKTLD/cpd_utils/_detection/kernels.h
src/scKTLD/cpd_utils/utils/__init__.py
src/scKTLD/cpd_utils/utils/bnode.py
src/scKTLD/cpd_utils/utils/drawbkps.py
src/scKTLD/cpd_utils/utils/utils.py
src/scKTLD/cpd_utils/utils/_utils/__init__.py
src/scKTLD/cpd_utils/utils/_utils/convert_path_matrix.c
src/scKTLD/cpd_utils/utils/_utils/convert_path_matrix.pxd
src/scKTLD/cpd_utils/utils/_utils/convert_path_matrix.pyx
src/scKTLD/cpd_utils/utils/_utils/convert_path_matrix_c.c
src/scKTLD/cpd_utils/utils/_utils/convert_path_matrix_c.h